jobpackage/AuthProvider.py
jobpackage/__init__.py
jobpackage-0.1.12.dist-info/METADATA
jobpackage-0.1.12.dist-info/WHEEL
jobpackage-0.1.12.dist-info/top_level.txt
jobpackage-0.1.12.dist-info/RECORD
