Metadata-Version: 2.1
Name: jobpackage
Version: 0.1.12
Summary: Package which allows for connection to jobpac using inputs
Author: Bryn Lom
Author-email: bryn.lom@edgeglobalsolutions.com
Classifier: Programming Language :: Python :: 3
Classifier: License :: OSI Approved :: MIT License
Classifier: Operating System :: OS Independent
Requires-Python: >=3.6
Requires-Dist: pycryptodome >=3.15.0
